eikobot/__init__.py
eikobot/__main__.py
eikobot/py.typed
eikobot/core/__init__.py
eikobot/core/deployer.py
eikobot/core/errors.py
eikobot/core/exporter.py
eikobot/core/handlers.py
eikobot/core/helpers.py
eikobot/core/logger.py
eikobot/core/plugin.py
eikobot/core/project.py
eikobot/core/compiler/__init__.py
eikobot/core/compiler/_parser.py
eikobot/core/compiler/_token.py
eikobot/core/compiler/decorator.py
eikobot/core/compiler/importlib.py
eikobot/core/compiler/lexer.py
eikobot/core/compiler/misc.py
eikobot/core/compiler/ops.py
eikobot/core/compiler/definitions/__init__.py
eikobot/core/compiler/definitions/_resource.py
eikobot/core/compiler/definitions/base_model.py
eikobot/core/compiler/definitions/base_types.py
eikobot/core/compiler/definitions/context.py
eikobot/core/compiler/definitions/function.py
eikobot/core/compiler/definitions/typedef.py
eikobot/core/lib/__init__.py
eikobot/core/lib/std/__init__.eiko
eikobot/core/lib/std/__init__.py
eikobot/core/lib/std/env.eiko
eikobot/core/lib/std/env.py
eikobot/core/lib/std/file.eiko
eikobot/core/lib/std/file.py
eikobot/core/lib/std/regex.eiko
eikobot/core/lib/std/regex.py
eikobot/core/lib/std/test.eiko
eikobot/core/lib/std/test.py
eikobot/core/package_manager/__init__.py
eikobot-0.7.8.dist-info/LICENSE
eikobot-0.7.8.dist-info/METADATA
eikobot-0.7.8.dist-info/WHEEL
eikobot-0.7.8.dist-info/entry_points.txt
eikobot-0.7.8.dist-info/top_level.txt
eikobot-0.7.8.dist-info/RECORD
