Metadata-Version: 2.1
Name: eikobot
Version: 0.7.8
Summary: The eikobot desired state engine.
Author: kazaamjt
Author-email: kazaamjt@gmail.com
License: MIT
Classifier: Programming Language :: Python :: 3
Classifier: License :: OSI Approved :: MIT License
Classifier: Operating System :: OS Independent
Classifier: Topic :: System :: Systems Administration
Classifier: Topic :: Utilities
Classifier: Intended Audience :: Developers
Classifier: Intended Audience :: Information Technology
Classifier: Intended Audience :: System Administrators
Classifier: Development Status :: 4 - Beta
Requires-Python: >=3.11
License-File: LICENSE
Requires-Dist: aiohttp >=3.8.6
Requires-Dist: asyncssh >=2.14.0
Requires-Dist: click >=8.1.7
Requires-Dist: colorama >=0.4.6
Requires-Dist: jinja2 >=3.1.2
Requires-Dist: packaging >=23.2
Requires-Dist: pydantic >=2.4.2
Requires-Dist: setuptools >=70.1.1
